anchor/__init__.py
anchor/admin.py
anchor/apps.py
anchor/checks.py
anchor/settings.py
anchor/urls.py
anchor/forms/__init__.py
anchor/forms/fields.py
anchor/forms/widgets.py
anchor/management/__init__.py
anchor/management/commands/__init__.py
anchor/management/commands/anchor_purge_unattached.py
anchor/migrations/0001_initial.py
anchor/migrations/__init__.py
anchor/models/__init__.py
anchor/models/attachment.py
anchor/models/base.py
anchor/models/variant.py
anchor/models/variant_record.py
anchor/models/variant_with_record.py
anchor/models/variation.py
anchor/models/blob/__init__.py
anchor/models/blob/blob.py
anchor/models/blob/keys.py
anchor/models/blob/representations.py
anchor/models/fields/__init__.py
anchor/models/fields/single_attachment.py
anchor/services/processors/__init__.py
anchor/services/processors/base.py
anchor/services/processors/pillow.py
anchor/services/transformers/__init__.py
anchor/services/transformers/base.py
anchor/services/transformers/image.py
anchor/services/urls/__init__.py
anchor/services/urls/base.py
anchor/services/urls/file_system.py
anchor/services/urls/s3.py
anchor/support/__init__.py
anchor/support/base58.py
anchor/support/signing.py
anchor/templates/anchor/widgets/admin_blob_input.html
anchor/templatetags/__init__.py
anchor/templatetags/anchor.py
anchor/views/__init__.py
anchor/views/blobs.py
anchor/views/file_system.py
anchor/views/representations.py
django_anchor-0.7.0.dist-info/licenses/LICENSE.md
django_anchor-0.7.0.dist-info/METADATA
django_anchor-0.7.0.dist-info/WHEEL
django_anchor-0.7.0.dist-info/top_level.txt
django_anchor-0.7.0.dist-info/RECORD
