Metadata-Version: 2.4
Name: django-anchor
Version: 0.7.0
Summary: Attach files to Django models
Author-email: Elias Hernandis <elias@hernandis.me>
License: Copyright (c) 2024 Elias Hernandis
Project-URL: Homepage, https://github.com/knifecake/django-anchor
Project-URL: Source, https://github.com/knifecake/django-anchor
Project-URL: Documentation, https://django-anchor.readthedocs.io/en/latest/
Project-URL: Tracker, https://github.com/knifecake/django-anchor/issues
Project-URL: Releases, https://github.com/knifecake/django-anchor/releases
Keywords: django,files,attachments
Classifier: Framework :: Django
Classifier: Framework :: Django :: 4.2
Classifier: Framework :: Django :: 5.0
Classifier: Framework :: Django :: 5.1
Classifier: Framework :: Django :: 5.2
Classifier: Framework :: Django :: 6.0
Classifier: Programming Language :: Python :: 3.11
Classifier: Programming Language :: Python :: 3.12
Classifier: Programming Language :: Python :: 3.13
Classifier: Operating System :: OS Independent
Classifier: License :: OSI Approved :: MIT License
Classifier: Natural Language :: English
Classifier: Topic :: File Formats
Classifier: Topic :: Internet :: WWW/HTTP :: Dynamic Content
Requires-Python: >=3.12
License-File: LICENSE.md
Requires-Dist: django>=4.2
Requires-Dist: pillow<12,>=9.5
Dynamic: license-file
